Z80.srcs/sources_1/new/Z80CU.v
// Zilog Z80 Project - INSTITUTO NACIONAL DE ATROFISICA OPTICA Y ELECTRONICA

// Z80 Controller Module
module Z80CU (

input iCLK,
input iRST,
input [7:0] iOPCODE,   
// Z80 External memory control signals
output wire oMREQ,
output wire oRD,
output wire oWR,
        
// Bus eneable
output wire oADR_EN,
output wire oIO_EN, 
        
// Z80 Internal control signals
output wire oLD_INSTREG,
output wire oLD_PC,
output wire oINC_PC,
output wire oWR_INT,
output wire [2:0] oWR_SEL,
output wire oRD_INT,
output wire [2:0] oRD_SEL);
//--------------------------------------------------------------------------
      
// No Blocking Assignments Control States
  reg [15:0] rSTATE_D;	reg [15:0] rSTATE_Q; 
  
// No Blocking Assignments External Memory Control Signals
  reg rMREQ;
  reg rRD;
  reg rWR;
  
// No Blocking Flip flop Assignments BUS eneable signals
  reg rADR_EN;
  reg rIO_EN;

// No Blocking Flip flop Assignments Internal Control Signals
  reg rLD_INSTREG;
  reg rLD_PC;
  reg rINC_PC;
  reg rWR_INT;
  reg [2:0] rWR_SEL;
  reg rRD_INT;
  reg [2:0] rRD_SEL;
  
// Output Assignments
  
 assign oMREQ = rMREQ;
 assign oRD = rRD;
 assign oWR = rWR;
 assign oADR_EN = rADR_EN;
 assign oIO_EN = rIO_EN;
 assign oLD_INSTREG = rLD_INSTREG;
 assign oLD_PC = rLD_PC;
 assign oINC_PC = rINC_PC;
 assign oWR_INT = rWR_INT;
 assign oWR_SEL = rWR_SEL;
 assign oRD_INT = rRD_INT;
 assign oRD_SEL =	rRD_SEL;

//Initial values of registers
initial 
  begin
      rSTATE_Q <= 16'h0000;
      rMREQ <= 1'b0;
      rRD <= 1'b0;
      rWR <= 1'b0;
      rADR_EN <= 1'b0;
      rIO_EN <= 1'b0;
      rLD_INSTREG <= 1'b0;
      rLD_PC <= 1'b0;
      rINC_PC <= 1'b0;
      rWR_INT <= 1'b0;
      rWR_SEL <= 3'b000;
      rRD_INT <= 1'b0;
      rRD_SEL <= 3'b000; 
    
      rSTATE_D <= 16'h0000;

end   
  
// Flip flops - Outputs Assignments 
  always @(posedge iCLK)
    begin
      rSTATE_Q <= rSTATE_D;
    end


// General secuential of States
  always @*
    begin
      if (iRST) begin
        rSTATE_D = 16'h0000;
      	end
      else begin
      		case(rSTATE_Q)
        	//Fetch------------------------------------------------------------------------------------------------
            //Initial STATE
        	16'h0000:
            begin
        	rSTATE_D = 16'h0001; rMREQ = 1'b0; rWR = 1'b0; rRD = 1'b0; 
            rADR_EN = 1'b0; rIO_EN = 1'b0; rLD_INSTREG = 1'b0; 		
            rLD_PC = 1'b0; 
            rINC_PC = 1'b0;
            rWR_INT = 1'b0;
            rWR_SEL = 3'b000;
            rRD_INT = 1'b0;
            rRD_SEL = 3'b000;
            end
           
            //Program Memorý Request
            16'h0001: 
            begin
        	rSTATE_D = 16'h0002; rMREQ = 1'b1; rWR = 1'b0; rRD = 1'b1; 
            rADR_EN = 1'b1; rIO_EN = 1'b1; rLD_INSTREG = 1'b0; 
            rLD_PC = 1'b0; rINC_PC = 1'b0; rWR_INT = 1'b0; 
            rRD_INT = 1'b0;  
            end
              
            //LD Instruction Register
            16'h0002:
            begin
        	rSTATE_D = 16'h0003; rMREQ = 1'b1; rWR = 1'b0; rRD = 1'b1; 
            rADR_EN = 1'b1; rIO_EN = 1'b1; rLD_INSTREG = 1'b1; 
            rLD_PC = 1'b0; rINC_PC = 1'b1; rWR_INT = 1'b0; rRD_INT = 1'b0; 
            end
              
            //DECODE------------------------------------------------------------------------------------------------
            16'h0003:	
            begin
            rMREQ = 1'b0; 
            rWR = 1'b0; 
            rRD = 1'b0; 
            rADR_EN = 1'b0; 
            rIO_EN = 1'b0; 
            rLD_INSTREG = 1'b0; 
            rLD_PC = 1'b0; 
            rINC_PC = 1'b0; 
            rWR_INT = 1'b0; 
            rRD_INT = 1'b0; 
              casex (iOPCODE)
        			8'b01xxxxxx:    //LD r<--r'
        			begin
          				if (iOPCODE[2:0] == 3'b110 || iOPCODE[5:3] == 3'b110) begin
          					rSTATE_D = 16'h0000; //Indirect adressing (pending)
          					end
          				else begin
            				rWR_SEL = iOPCODE[5:3];
            				rRD_SEL = iOPCODE[2:0];
            				rSTATE_D = 16'h0004;  
          				end
        			end
        
       				8'b00xxx110:    //LD r<--n
        			begin
          				if (iOPCODE[5:3] == 3'b110) begin
            				rSTATE_D = 16'h0000; //Indirect adressing (pending)
            				end
          				else begin
            				rWR_SEL = iOPCODE[5:3]; 
            				rSTATE_D = 16'h0006;
          				end
       		 		end
         
        			default: rSTATE_D = 16'h0000; //To Fetch Instruction States
       
     				endcase
            end
            //------------------------------------------------------------------------------------------------------
              
            //LD r<--r'
            16'h0004:
            begin
            rSTATE_D = 16'h0005; rMREQ = 1'b0; rWR = 1'b0; rRD = 1'b0; 
            rADR_EN = 1'b0; rIO_EN = 1'b0; rLD_INSTREG = 1'b0; 
            rLD_PC = 1'b0; rINC_PC = 1'b0; rWR_INT = 1'b0;
            rRD_INT = 1'b1; 
            end
            
            16'h0005:
            begin
            rSTATE_D = 16'h0000; rMREQ = 1'b0; rWR = 1'b0; rRD = 1'b0; 
            rADR_EN = 1'b0; rIO_EN = 1'b0; rLD_INSTREG = 0; 
            rLD_PC = 1'b0; rINC_PC = 1'b0; rWR_INT = 1'b1; 
            rRD_INT = 1'b1;
            end
              
            //LD r<--n
            16'h0006:
            begin
            rSTATE_D = 16'h0007; rMREQ = 1'b1; rWR = 1'b0; rRD = 1'b0; 
            rADR_EN = 1'b0; rIO_EN = 1'b1; rLD_INSTREG = 1'b0; 
            rLD_PC = 1'b0; rINC_PC = 1'b1; rWR_INT = 1'b0; 
            rRD_INT = 1'b0; 
            end
            
            16'h0007:
            begin
            rSTATE_D = 16'h0000; rMREQ = 1'b1; rWR = 1'b0; rRD = 1'b1; 
            rADR_EN = 1'b1; rIO_EN = 1'b1; rLD_INSTREG = 1'b0; 
            rLD_PC = 1'b0; rINC_PC = 1'b0; rWR_INT = 1'b1;
            rRD_INT = 1'b0; 
            end
            
            default rSTATE_D = 16'h0000;
            
            endcase
    	end
end
endmodule

Z80.srcs/sim_1/new/Z80CU_TB.v
//ZILOG Z80 Control Unit Test Bench
`timescale 1ns/1ps
module Z80CU_TB();
  reg CLK; 
  reg RST_TB;
  reg [2:0] ADR1;
  reg [2:0] ADR2;
  reg [7:0] OPCODE_TB;
  wire MREQ_TB;
  wire RD_TB;
  wire WR_TB;
  wire ADR_EN_TB;
  wire IO_EN_TB;
  wire LD_INSTREG_TB;
  wire LD_PC_TB;
  wire INC_PC_TB;
  wire WR_INT_TB;
  wire [2:0] WR_SEL_TB; 
  wire RD_INT_TB; 
  wire [2:0] RD_SEL_TB; 
   
Z80CU DUT (.iCLK(CLK),
           .iRST(RST_TB), 
           .iOPCODE(OPCODE_TB), 
           .oMREQ(MREQ_TB), 
           .oRD(RD_TB), 
           .oWR(WR_TB), 
           .oADR_EN(ADR_EN_TB), 
           .oIO_EN(IO_EN_TB), 
           .oLD_INSTREG(LD_INSTREG_TB), 
           .oLD_PC(LD_PC_TB), 
           .oINC_PC(INC_PC_TB), 
           .oWR_INT(WR_INT_TB), 
           .oWR_SEL(WR_SEL_TB), 
           .oRD_INT(RD_INT_TB), 
           .oRD_SEL(RD_SEL_TB));

//OPCODES FILE REGISTER'S ADRESSES
//assign ADR1 = 3'b011;
//assign   ADR2 = 3'b101; //Las moví adentro del initial XD
  
initial begin
  CLK <= 1'b0;
  RST_TB <= 1'b0;
  assign ADR1 = 3'b011;
  assign   ADR2 = 3'b101;
  //LD r(ADR1)<---r'(ADR2)
  OPCODE_TB <= {2'b01, ADR1, ADR2};
  
  //LD r(ADR1)<---n
  #100 OPCODE_TB <= {2'b00, ADR1, 3'b110};
  #160
  
  //RESET AND FETCH LOOP
  OPCODE_TB <= 8'h00;
  RST_TB <= 1'b1;
  #20 RST_TB <= 1'b0;
  #100 $finish; 
  end
  
always begin
    #10;
  	CLK <= ~CLK;
	end
	
  
initial begin
    $dumpvars;
    $dumpfile("dump.vcd");
  end   
  
endmodule

Z80.sim/sim_1/behav/xsim/dump.vcd
$date
   Thu Nov 24 17:21:11 2022
$end
$version
  2022.2
$end
$timescale
  1ps
$end
$scope module Z80CU_TB $end
$var reg 1 ! CLK $end
$var reg 1 " RST_TB $end
$var reg 3 # ADR1 [2:0] $end
$var reg 3 $ ADR2 [2:0] $end
$var reg 8 % OPCODE_TB [7:0] $end
$var wire 1 & MREQ_TB $end
$var wire 1 ' RD_TB $end
$var wire 1 ( WR_TB $end
$var wire 1 ) ADR_EN_TB $end
$var wire 1 * IO_EN_TB $end
$var wire 1 + LD_INSTREG_TB $end
$var wire 1 , LD_PC_TB $end
$var wire 1 - INC_PC_TB $end
$var wire 1 . WR_INT_TB $end
$var wire 3 / WR_SEL_TB [2:0] $end
$var wire 1 0 RD_INT_TB $end
$var wire 3 1 RD_SEL_TB [2:0] $end
$scope module DUT $end
$var wire 1 2 iCLK $end
$var wire 1 3 iRST $end
$var wire 8 4 iOPCODE [7:0] $end
$var wire 1 & oMREQ $end
$var wire 1 ' oRD $end
$var wire 1 ( oWR $end
$var wire 1 ) oADR_EN $end
$var wire 1 * oIO_EN $end
$var wire 1 + oLD_INSTREG $end
$var wire 1 , oLD_PC $end
$var wire 1 - oINC_PC $end
$var wire 1 . oWR_INT $end
$var wire 3 / oWR_SEL [2:0] $end
$var wire 1 0 oRD_INT $end
$var wire 3 1 oRD_SEL [2:0] $end
$var reg 16 5 rSTATE_D [15:0] $end
$var reg 16 6 rSTATE_Q [15:0] $end
$var reg 1 7 rMREQ $end
$var reg 1 8 rRD $end
$var reg 1 9 rWR $end
$var reg 1 : rADR_EN $end
$var reg 1 ; rIO_EN $end
$var reg 1 < rLD_INSTREG $end
$var reg 1 = rLD_PC $end
$var reg 1 > rINC_PC $end
$var reg 1 ? rWR_INT $end
$var reg 3 @ rWR_SEL [2:0] $end
$var reg 1 A rRD_INT $end
$var reg 3 B rRD_SEL [2:0] $end
$upscope $end
$upscope $end
$enddefinitions $end
#0
$dumpvars
0!
0"
b11 #
b101 $
b1011101 %
0&
0'
0(
0)
0*
0+
0,
0-
0.
b0 /
00
b0 1
02
03
b1011101 4
b1 5
b0 6
07
08
09
0:
0;
0<
0=
0>
0?
b0 @
0A
b0 B
$end
#10000
1!
1&
1'
1)
1*
12
b10 5
b1 6
17
18
1:
1;
#20000
0!
02
#30000
1!
1+
1-
12
b11 5
b10 6
1<
1>
#40000
0!
02
#50000
1!
0&
0'
0)
0*
0+
0-
b11 /
b101 1
12
b100 5
b11 6
07
08
0:
0;
0<
0>
b11 @
b101 B
#60000
0!
02
#70000
1!
10
12
b101 5
b100 6
1A
#80000
0!
02
#90000
1!
1.
12
b0 5
b101 6
1?
#100000
0!
b11110 %
02
b11110 4
b0 5
#110000
1!
0.
b0 /
00
b0 1
12
b1 5
b0 6
0?
b0 @
0A
b0 B
#120000
0!
02
#130000
1!
1&
1'
1)
1*
12
b10 5
b1 6
17
18
1:
1;
#140000
0!
02
#150000
1!
1+
1-
12
b11 5
b10 6
1<
1>
#160000
0!
02
#170000
1!
0&
0'
0)
0*
0+
0-
b11 /
12
b110 5
b11 6
07
08
0:
0;
0<
0>
b11 @
#180000
0!
02
#190000
1!
1&
1*
1-
12
b111 5
b110 6
17
1;
1>
#200000
0!
02
#210000
1!
1'
1)
0-
1.
12
b0 5
b111 6
18
1:
0>
1?
#220000
0!
02
#230000
1!
0&
0'
0)
0*
0.
b0 /
12
b1 5
b0 6
07
08
0:
0;
0?
b0 @
b0 B
#240000
0!
02
#250000
1!
1&
1'
1)
1*
12
b10 5
b1 6
17
18
1:
1;
#260000
0!
1"
b0 %
02
13
b0 4
b0 5
#270000
1!
12
b0 5
b0 6
#280000
0!
0"
0&
0'
0)
0*
02
03
b1 5
07
08
0:
0;
b0 @
b0 B
#290000
1!
1&
1'
1)
1*
12
b10 5
b1 6
17
18
1:
1;
#300000
0!
02
#310000
1!
1+
1-
12
b11 5
b10 6
1<
1>
#320000
0!
02
#330000
1!
0&
0'
0)
0*
0+
0-
12
b0 5
b11 6
07
08
0:
0;
0<
0>
#340000
0!
02
#350000
1!
12
b1 5
b0 6
b0 @
b0 B
